pycosmos/__init__.py
pycosmos/cosmos_project.py
pycosmos-0.11.dist-info/LICENSE
pycosmos-0.11.dist-info/METADATA
pycosmos-0.11.dist-info/WHEEL
pycosmos-0.11.dist-info/top_level.txt
pycosmos-0.11.dist-info/RECORD
