Metadata-Version: 2.1
Name: pycosmos
Version: 0.11
Summary: A python judging client library for Cosmos front-ends
Home-page: https://github.com/phulsechinmay/pycosmos
Author: Chinmay Phulse
Author-email: phulsechinmay@gmail.com
License: UNKNOWN
Download-URL: https://github.com/phulsechinmay/pycosmos/archive/v_011.tar.gz
Platform: UNKNOWN
Classifier: Programming Language :: Python :: 3
Classifier: License :: OSI Approved :: MIT License
Classifier: Operating System :: OS Independent
Requires-Dist: requests
Requires-Dist: pandas
Requires-Dist: numpy
